jes4py/Config.py
jes4py/FileChooser.py
jes4py/Picture.py
jes4py/PixelColor.py
jes4py/Sample.py
jes4py/Samples.py
jes4py/Sound.py
jes4py/SoundSample.py
jes4py/__init__.py
jes4py/colorPicker.py
jes4py/filePicker.py
jes4py/media.py
jes4py/pictureTool.py
jes4py/show.py
jes4py/images/Left.png
jes4py/images/Right.png
jes4py/scripts/colorPicker.py
jes4py/scripts/filePicker.py
jes4py/scripts/pictureTool.py
jes4py/scripts/images/Left.png
jes4py/scripts/images/Right.png
jes4py-0.1.7.dist-info/LICENSE
jes4py-0.1.7.dist-info/METADATA
jes4py-0.1.7.dist-info/WHEEL
jes4py-0.1.7.dist-info/top_level.txt
jes4py-0.1.7.dist-info/RECORD
