Metadata-Version: 2.1
Name: jes4py
Version: 0.1.7
Summary: Python 3 package providing a subset of JES's media functionality
Home-page: https://github.com/gordon-cs/JES4py
Author: Jonathan Senning
Author-email: jonathan.senning@gordon.edu
License: UNKNOWN
Platform: UNKNOWN
Classifier: Programming Language :: Python :: 3
Classifier: License :: OSI Approved :: GNU General Public License v3 (GPLv3)
Classifier: Operating System :: OS Independent
Requires-Python: >=3.6.0
License-File: LICENSE
Requires-Dist: simpleaudio
Requires-Dist: wave
Requires-Dist: wxPython
